{
  "users": [
    {
      "email": "bw@test.com",
      "password": "$2a$10$riPYxtfpbgiYbRwBfqgx9.DfmvyGG2stc.2K9nf0UxLKg9JGYMuMW",
      "id": 1739499634814,
      "username": "Brian",
      "name": "Brian W.",
      "bankAccount": "123456789",
      "balance": 149230.55
    },
    {
      "email": "rudy@test.com",
      "password": "$2a$10$zxgYAW9TNyHFseMu9SzYOuf93lDhCO6el9B7keSX5FnGn80TNe9Ai",
      "id": 1740074987696,
      "name": "Rudy Weiler",
      "bankAccount": "123456789",
      "balance": 97358.47
    },
    {
      "email": "brian@test.com",
      "password": "$2a$10$kR9h3CGOoV5Y/E2snxgNV.gx02qLs2NImMrlrFvguYMQ1IMxbAdxO",
      "id": 1740420401403,
      "name": "Brian Whisenhunt",
      "bankAccount": "789456123",
      "balance": 82292.04
    }
  ],
  "transactions": [
    {
      "user_id": 1740074987696,
      "name": "Ethereum",
      "symbol": "ETH",
      "amount": 1,
      "buyDate": 1740171963015,
      "buyPrice": 2641.53,
      "id": 27
    },
    {
      "user_id": 1740074987696,
      "name": "Ethereum",
      "symbol": "ETH",
      "amount": 1,
      "buyDate": 1740172010751,
      "buyPrice": 2641.53,
      "id": 28
    },
    {
      "user_id": 1740074987696,
      "name": "Ethereum",
      "symbol": "ETH",
      "amount": 1,
      "buyDate": 1740172142401,
      "buyPrice": 2641.53,
      "id": 29
    },
    {
      "user_id": 1739499634814,
      "name": "Solana",
      "symbol": "SOL",
      "amount": 5,
      "buyDate": 1740416979682,
      "buyPrice": 153.89,
      "id": 30
    },
    {
      "user_id": 1740420401403,
      "name": "Bitcoin",
      "symbol": "BTC",
      "amount": 1,
      "buyDate": 1740451915437,
      "buyPrice": 92503.66,
      "id": 31
    },
    {
      "user_id": 1740420401403,
      "name": "Ethereum",
      "symbol": "ETH",
      "amount": 10,
      "buyDate": 1740451949374,
      "buyPrice": 2520.43,
      "id": 32
    }
  ],
  "cryptos": [
    {
      "user_id": 1740074987696,
      "name": "Ethereum",
      "symbol": "ETH",
      "amount": 1,
      "id": 27
    },
    {
      "user_id": 1740074987696,
      "name": "Ethereum",
      "symbol": "ETH",
      "amount": 1,
      "id": 28
    },
    {
      "user_id": 1740074987696,
      "name": "Ethereum",
      "symbol": "ETH",
      "amount": 1,
      "id": 29
    },
    {
      "user_id": 1739499634814,
      "name": "Solana",
      "symbol": "SOL",
      "amount": 5,
      "id": 30
    },
    {
      "user_id": 1740420401403,
      "name": "Bitcoin",
      "symbol": "BTC",
      "amount": 1,
      "id": 31
    },
    {
      "user_id": 1740420401403,
      "name": "Ethereum",
      "symbol": "ETH",
      "amount": 10,
      "id": 32
    }
  ]
}